api_swedeb/__init__.py
api_swedeb/api/__init__.py
api_swedeb/api/metadata_router.py
api_swedeb/api/parlaclarin/__init__.py
api_swedeb/api/parlaclarin/__paths__.py
api_swedeb/api/tool_router.py
api_swedeb/api/utils/__init__.py
api_swedeb/api/utils/common_params.py
api_swedeb/api/utils/corpus.py
api_swedeb/api/utils/dependencies.py
api_swedeb/api/utils/kwic.py
api_swedeb/api/utils/metadata.py
api_swedeb/api/utils/ngrams.py
api_swedeb/api/utils/speech.py
api_swedeb/api/utils/topics.py
api_swedeb/api/utils/word_trends.py
api_swedeb/core/__init__.py
api_swedeb/core/codecs.py
api_swedeb/core/configuration/__init__.py
api_swedeb/core/configuration/config.py
api_swedeb/core/configuration/inject.py
api_swedeb/core/cwb/__init__.py
api_swedeb/core/cwb/compiler.py
api_swedeb/core/cwb/utility.py
api_swedeb/core/kwic/__init__.py
api_swedeb/core/kwic/complex.py
api_swedeb/core/kwic/simple.py
api_swedeb/core/load.py
api_swedeb/core/n_grams/__init__.py
api_swedeb/core/n_grams/compute.py
api_swedeb/core/speech.py
api_swedeb/core/speech_index.py
api_swedeb/core/speech_text.py
api_swedeb/core/utility.py
api_swedeb/core/word_trends.py
api_swedeb/mappers/__init__.py
api_swedeb/mappers/cqp_opts.py
api_swedeb/mappers/ngrams.py
api_swedeb/schemas/__init__.py
api_swedeb/schemas/kwic_schema.py
api_swedeb/schemas/metadata_schema.py
api_swedeb/schemas/ngrams_schema.py
api_swedeb/schemas/sort_order.py
api_swedeb/schemas/speech_text_schema.py
api_swedeb/schemas/speeches_schema.py
api_swedeb/schemas/topics_schema.py
api_swedeb/schemas/word_trends_schema.py
api_swedeb-0.2.12.dist-info/METADATA
api_swedeb-0.2.12.dist-info/WHEEL
api_swedeb-0.2.12.dist-info/RECORD
