Metadata-Version: 2.3
Name: api-swedeb
Version: 0.2.12
Summary: 
Author: rebeckaw
Author-email: rebecka.weegar@umu.se
Requires-Python: ==3.11.*
Classifier: Programming Language :: Python :: 3
Classifier: Programming Language :: Python :: 3.11
Requires-Dist: cwb-ccc
Requires-Dist: fastapi
Requires-Dist: humlab-penelope (>=0.8.2,<0.9.0)
Requires-Dist: numpy
Requires-Dist: pyarrow
Requires-Dist: pydantic
Requires-Dist: python-dotenv
Requires-Dist: scipy
Requires-Dist: uvicorn[standard] (>=0.24.0.post1,<0.25.0)
